{
  "$schema": "https://mintlify.com/schema.json",
  "name": "Runbear",
  "logo": {
    "dark": "/logo/dark.svg",
    "light": "/logo/light.svg"
  },
  "favicon": "/favicon.png",
  "colors": {
    "primary": "#12A7D3",
    "light": "#81D7F7",
    "dark": "#004E7A"
  },
  "topbarLinks": [
    {
      "name": "Contact us",
      "url": "mailto:contact@runbear.io"
    }
  ],
  "topbarCtaButton": {
    "name": "Get started",
    "url": "https://app.runbear.io"
  },
  "tabs": [],
  "navigation": [
    {
      "group": "Get Started",
      "pages": [
        "introduction",
        "slack-integration",
        "runbook-management",
        "runbook-execution",
        "setup-worker"
      ]
    },
    {
      "group": "Use Cases",
      "pages": [
        "use-cases/answering-questions",
        "use-cases/checking-service-status",
        "use-cases/incident-response",
        "use-cases/troubleshooting-guide",
        "use-cases/retrieving-data",
        "use-cases/keeping-conversation",
        "use-cases/slack-request-form",
        "use-cases/slack-bookmark"
      ]
    },
    {
      "group": "Under the Hood",
      "pages": [
        "under-the-hood/faq"
      ]
    }
  ],
  "footerSocials": {
    "twitter": "https://twitter.com/runbear_io",
    "github": "https://github.com/runbear-io",
    "linkedin": "https://www.linkedin.com/company/runbear"
  },
  "backgroundImage": "/background.png"
}
